controller/__init__.py
controller/task_controller.py
model/__init__.py
model/task.py
model/tasklist.py
project_big_data-0.1.0.dist-info/METADATA
project_big_data-0.1.0.dist-info/WHEEL
project_big_data-0.1.0.dist-info/top_level.txt
project_big_data-0.1.0.dist-info/RECORD
