Metadata-Version: 2.1
Name: project-big-data
Version: 0.1.0
Summary: ToDo list du projet kit big data
Author: Guillaume, Paul, Aleksander, Lucas, Guillaume
Classifier: Programming Language :: Python :: 3.9
Classifier: Operating System :: OS Independent
Requires-Python: >=3.9
Requires-Dist: datetime ==5.2
Requires-Dist: pymongo ==4.5.0
Requires-Dist: gradio ==3.50.2
Requires-Dist: pytest ==7.4.3
Requires-Dist: pytest-cov ==4.1.0
Requires-Dist: sphinx ==7.2.6
Requires-Dist: mongomock ==4.1.2
Requires-Dist: argparse ==1.4.0
